{
  "bodies": {
    "body_mizai_001": {
      "front": "keke-assassin",
      "extra": "keke-assassin-mega"
    },
    "body_trans_001": {
      "front": "baizi-body",
      "extra": "baizi-body-mega-v2"
    },
    "body_combo_001": {
      "front": "guamao-body",
      "extra": "guamao-body-mega"
    },
    "body_aggro_001": {
      "front": "weixiao-body",
      "extra": "weixiao-body-mega"
    },
    "body_dispatch_001": {
      "front": "aichitun-body",
      "extra": "aichitun-body-z-move"
    },
    "body_ambush_001": {
      "front": "xiaoapan-body",
      "extra": "xiaoapan-body-z-move"
    },
    "body_blood_001": {
      "front": "fengyaojing-body",
      "extra": "fengyaojing-body-z-move"
    }
  },
  "characters": {
    "char_001_keke_assassin": "keke-assassin",
    "char_007_baizi_ninja": "baizi-ninja",
    "char_008_baizi_hitman": "baizi-hitman",
    "char_011_baizi_bomber": "baizi-bomber",
    "char_012_baizi_bird-eater": "baizi-bird-eater",
    "char_014_baizi_party-duck": "baizi-party-duck",
    "char_016_baizi_gravy": "baizi-gravy",
    "char_018_baizi_defect-robot": "baizi-defect-robot",
    "char_020_baizi_ironclad": "baizi-ironclad",
    "char_025_baizi_high-priest": "baizi-high-priest",
    "char_029_baizi_silent-hunter": "baizi-silent-hunter",
    "char_041_baizi_watcher": "baizi-watcher",
    "char_043_baizi_falcon": "baizi-falcon",
    "char_051_baizi_lobbyist": "baizi-lobbyist",
    "char_060_linglong_defect-robot": "linglong-defect-robot",
    "char_066_linglong_ninja": "linglong-ninja",
    "char_054_xiangcai_prophet": "xiangcai-prophet-resource-v3-guamao",
    "char_058_xiangcai_politician": "xiangcai-politician-final",
    "char_061_xiangcai_watcher": "xiangcai-watcher-resource-v3",
    "char_067_xiangcai_neo": "xiangcai-neo-resource-v3",
    "char_071_baizi_red-wolf": "baizi-red-wolf",
    "char_075_baizi_weilong": "baizi-weilong",
    "char_052_fengyaojing_desert-butcher": "fengyaojing-desert-butcher-v2",
    "char_003_qindi_sheriff": "qindi-sheriff",
    "char_004_horus-lupercal_pelican": "horus-lupercal-pelican",
    "char_053_xiaoka_zaun-beast": "xiaoka-zaun-beast",
    "char_040_fengyaojing_detective": "fengyaojing-detective",
    "char_034_xiaoapan_avenger": "xiaoapan-avenger",
    "char_021_xiaoapan_warlock": "xiaoapan-warlock",
    "char_035_xiaoapan_silent-hunter": "xiaoapan-silent-hunter",
    "char_042_xiaoapan_neo": "xiaoapan-neo",
    "char_049_xiaoapan_undertaker": "xiaoapan-undertaker",
    "char_055_xiaoapan_judge": "xiaoapan-judge",
    "char_073_xiaoapan_bee-medic": "xiaoapan-bee-medic",
    "char_077_xiaoapan_shepherd": "xiaoapan-shepherd",
    "char_045_guamao_assassin": "guamao-assassin",
    "char_057_guamao_silent-hunter": "guamao-silent-hunter",
    "char_062_guamao_morphling": "guamao-morphling",
    "char_079_xiaoka_visionary-painter": "xiaoka-visionary-painter-v1",
    "char_046_fengyaojing_watcher": "fengyaojing-watcher-v1",
    "char_048_xiaoka_high-priest": "xiaoka-high-priest-v1",
    "char_019_dong_defect-robot": "dong-defect-robot-v1",
    "char_050_dong_bomber": "dong-bomber-v1",
    "char_065_dong_high-priest": "dong-high-priest-v1",
    "char_069_dong_sheriff": "dong-sheriff-v1",
    "char_059_dong_justice": "dong-justice-v1",
    "char_063_dong_assassin": "dong-assassin-v1",
    "char_017_huihuan_defect-robot": "huihuan-defect-robot-v1",
    "char_056_huihuan_watcher": "huihuan-watcher-v1",
    "char_064_huihuan_pelican": "huihuan-pelican-v1",
    "char_068_huihuan_bird-eater": "huihuan-bird-eater-v1",
    "char_070_huihuan_silent-hunter": "huihuan-silent-hunter-v1",
    "char_074_huihuan_nameless": "huihuan-nameless-v1",
    "char_078_huihuan_deep-blue": "huihuan-deep-blue-v1",
    "char_080_huihuan_visionary-painter": "huihuan-visionary-painter-v1"
  }
}
